alex_music.py
alex_music-0.0.3.dist-info/METADATA
alex_music-0.0.3.dist-info/WHEEL
alex_music-0.0.3.dist-info/licenses/LICENSE
alex_music-0.0.3.dist-info/RECORD
